[{"articleId":"art0","link":"https://vnexpress.net/785384829","title":"","publicationDate":"2549-01-23"},{"articleId":"art1","link":"https://dantri.com.vn/363706199","title":"","publicationDate":"2075-06-03"},{"articleId":"art2","link":"https://laodong.vn/435740969","title":"","publicationDate":"2516-10-23"},{"articleId":"art3","link":"https://tuoitre.vn/367149559","title":"","publicationDate":"2354-03-03"},{"articleId":"art4","link":"https://laodong.vn/686632202","title":"","publicationDate":"2691-12-22"}]