[{"name":"Số 184 Nguyễn Huệ, Hà Nội","description":"","country":"Việt Nam","entityId":"loc0","entityName":"location"},{"name":"Số 337 Số 33, Hồ Chí Minh","description":"","country":"Việt Nam","entityId":"loc1","entityName":"location"},{"name":"Số 168 Cầu Vượt Tỉnh Lộ 10, Hồ Chí Minh","description":"","country":"Việt Nam","entityId":"loc2","entityName":"location"},{"name":"Số 155 Lê Hồng Phong, Hồ Chí Minh","description":"","country":"Việt Nam","entityId":"loc3","entityName":"location"},{"name":"Số 441 Cao Thắng, Hồ Chí Minh","description":"","country":"Việt Nam","entityId":"loc4","entityName":"location"},{"name":"Số 276 Tôn Đức Thắng, Hồ Chí Minh","description":"","country":"Việt Nam","entityId":"loc5","entityName":"location"},{"name":"Số 402 Lê Thánh Tôn, Hồ Chí Minh","description":"","country":"Việt Nam","entityId":"loc6","entityName":"location"},{"name":"Số 499 Lê Văn Qưới, Hồ Chí Minh","description":"","country":"Việt Nam","entityId":"loc7","entityName":"location"},{"name":"Số 141 Hẻm Tôn Thất Tùng, Hồ Chí Minh","description":"","country":"Việt Nam","entityId":"loc8","entityName":"location"},{"name":"Số 331 Trần Quốc Toản, Hồ Chí Minh","description":"","country":"Việt Nam","entityId":"loc9","entityName":"location"}]